timevery/__init__.py
timevery/timer.py
timevery-0.1.8.dist-info/LICENSE
timevery-0.1.8.dist-info/METADATA
timevery-0.1.8.dist-info/WHEEL
timevery-0.1.8.dist-info/top_level.txt
timevery-0.1.8.dist-info/RECORD
