Metadata-Version: 2.1
Name: timevery
Version: 0.1.8
Summary: Monitor the time cost of your code easily.
Author-email: Shi Changshan <changshanshi@outlook.com>
License: MIT License
Project-URL: Homepage, https://github.com/Bardreamaster/timevery
Keywords: timer
Classifier: License :: OSI Approved :: MIT License
Classifier: Programming Language :: Python :: 3
License-File: LICENSE
Requires-Dist: rich
